config/__init__.py
config/config.py
main/__init__.py
main/main_sse.py
main/main_stdio.py
mcp_metricflow-1.0.0.dist-info/METADATA
mcp_metricflow-1.0.0.dist-info/WHEEL
mcp_metricflow-1.0.0.dist-info/entry_points.txt
mcp_metricflow-1.0.0.dist-info/licenses/LICENSE
server/__init__.py
server/auth.py
server/sse_server.py
server/stdio_server.py
tools/__init__.py
tools/cli_tools.py
tools/metricflow/__init__.py
tools/metricflow/base.py
tools/metricflow/health_checks.py
tools/metricflow/list_dimension_values.py
tools/metricflow/list_dimensions.py
tools/metricflow/list_entities.py
tools/metricflow/list_metrics.py
tools/metricflow/query.py
tools/metricflow/validate_configs.py
tools/prompts/__init__.py
tools/prompts/mf_cli/__init__.py
tools/prompts/mf_cli/health_checks.md
tools/prompts/mf_cli/list_dimension_values.md
tools/prompts/mf_cli/list_dimensions.md
tools/prompts/mf_cli/list_entities.md
tools/prompts/mf_cli/list_metrics.md
tools/prompts/mf_cli/query.md
tools/prompts/mf_cli/validate_configs.md
utils/__init__.py
utils/logger.py
utils/prompts.py
mcp_metricflow-1.0.0.dist-info/RECORD
