Metadata-Version: 2.1
Name: mcp-metricflow
Version: 1.0.0
Summary: A Model Context Protocol (MCP) server that provides MetricFlow CLI tools
License: MIT License
Requires-Python: >=3.10
Requires-Dist: fastapi>=0.115.12
Requires-Dist: uvicorn>=0.34.2
Requires-Dist: dbt-metricflow>=0.8.2
Requires-Dist: python-dotenv>=1.1.0
Requires-Dist: mcp>=1.3.2
Provides-Extra: snowflake
Requires-Dist: dbt-snowflake>=1.8.0; extra == "snowflake"
Provides-Extra: dev
Requires-Dist: black>=25.1.0; extra == "dev"
Requires-Dist: ruff<=0.11.10,>=0.11.0; extra == "dev"
Requires-Dist: bandit>=1.8.3; extra == "dev"
Requires-Dist: pre-commit>=4.2.0; extra == "dev"
Requires-Dist: poethepoet>=0.34.0; extra == "dev"
Provides-Extra: test
Requires-Dist: pytest>=8.0.0; extra == "test"
Requires-Dist: pytest-asyncio>=0.25.0; extra == "test"
Requires-Dist: pytest-cov>=6.0.0; extra == "test"
Requires-Dist: pytest-mock>=3.14.0; extra == "test"
Requires-Dist: pytest-sugar>=1.0.0; extra == "test"
Requires-Dist: coverage[toml]>=7.6.0; extra == "test"
